virtual_mechanism/__init__.py
virtual_mechanism/__main__.py
virtual_mechanism/dbc/clamp.dbc
virtual_mechanism/mechanisms/mechanism.py
virtual_mechanism/mechanisms/simple_clamp.py
virtual_mechanism-0.0.1.dist-info/METADATA
virtual_mechanism-0.0.1.dist-info/WHEEL
virtual_mechanism-0.0.1.dist-info/entry_points.txt
virtual_mechanism-0.0.1.dist-info/top_level.txt
virtual_mechanism-0.0.1.dist-info/RECORD
