Metadata-Version: 2.4
Name: virtual-mechanism
Version: 0.0.1
Summary: virtual mechanism for mock and test
Author-email: Pride Leong <lykling.lyk@gmail.com>
Project-URL: Homepage, https://github.com/lykling/virtual-mechanism/tree/main
Project-URL: Bug Tracker, https://github.com/lykling/virtual-mechanism/issues
Requires-Python: >3.6
Requires-Dist: cantools
Requires-Dist: click
Requires-Dist: python-can
Requires-Dist: setuptools
